piu/__init__.py
piu/__main__.py
piu/cli.py
piu/error_handling.py
piu/utils.py
stups_piu-1.2.5.dist-info/DESCRIPTION.rst
stups_piu-1.2.5.dist-info/METADATA
stups_piu-1.2.5.dist-info/RECORD
stups_piu-1.2.5.dist-info/WHEEL
stups_piu-1.2.5.dist-info/entry_points.txt
stups_piu-1.2.5.dist-info/metadata.json
stups_piu-1.2.5.dist-info/top_level.txt
