Metadata-Version: 2.0
Name: stups-piu
Version: 1.2.5
Summary: Command line client for "even" SSH access granting service
Home-page: https://github.com/zalando-stups/piu
Author: Henning Jacobs
Author-email: henning.jacobs@zalando.de
License: Apache License 2.0
Keywords: aws account saml login federated shibboleth
Platform: UNKNOWN
Classifier: Development Status :: 4 - Beta
Classifier: Environment :: Console
Classifier: Intended Audience :: Developers
Classifier: Intended Audience :: System Administrators
Classifier: License :: OSI Approved :: Apache Software License
Classifier: Operating System :: POSIX :: Linux
Classifier: Programming Language :: Python
Classifier: Programming Language :: Python :: 3.4
Classifier: Programming Language :: Python :: Implementation :: CPython
Requires-Dist: PyYAML
Requires-Dist: boto3 (>=1.17.33)
Requires-Dist: botocore (>=1.20.33)
Requires-Dist: click (>=1.2.2)
Requires-Dist: clickclick (>=0.10)
Requires-Dist: pyperclip
Requires-Dist: requests
Requires-Dist: sshpubkeys (>=3.1.0)
Requires-Dist: stups-zign (>=1.1.26)
